librsid.so
rsid_py.cpython-310-x86_64-linux-gnu.so
__init__.py
rsid_py.pyi
realsenseid-0.38.2.dist-info/TPP for Intel RealSense ID Vision Library Open Source.pdf
realsenseid-0.38.2.dist-info/Intel Copyrights.pdf
realsenseid-0.38.2.dist-info/WHEEL
realsenseid-0.38.2.dist-info/RECORD
realsenseid-0.38.2.dist-info/METADATA
realsenseid-0.38.2.dist-info/OBL license for Intel RealSense ID Vision Library for Face Authentication (BAO 3.8.21) 1.pdf
realsenseid-0.38.2.dist-info/top_level.txt
realsenseid-0.38.2.dist-info/TPP for Intel RealSense ID Vision Library FW.pdf
realsenseid-0.38.2.dist-info/LICENSE
