Metadata-Version: 2.1
Name: realsenseid
Version: 0.38.2
Summary: RealSenseID(TM)
Home-page: https://github.com/IntelRealSense/RealSenseID
Download-URL: https://github.com/IntelRealSense/RealSenseID/releases
Author: Intel(R) Corporation
Author-email: "Intel(R) Corporation" <realsenseid@intel.com>
License: OSI Approved :: Apache Software License
Project-URL: Homepage, https://www.intelrealsense.com/facial-authentication/
Project-URL: Documentation, https://github.com/IntelRealSense/RealSenseID/blob/master/Readme.md
Project-URL: Repository, https://github.com/IntelRealSense/RealSenseID
Project-URL: Issues, https://github.com/IntelRealSense/RealSenseID/issues
Project-URL: Changelog, https://github.com/IntelRealSense/RealSenseID/releases
Keywords: intel,realsense,realsenseid,facial-authentication
Classifier: Development Status :: 5 - Production/Stable
Classifier: Environment :: Console
Classifier: Intended Audience :: Developers
Classifier: Intended Audience :: Education
Classifier: Intended Audience :: Information Technology
Classifier: Intended Audience :: Science/Research
Classifier: License :: OSI Approved :: Apache Software License
Classifier: Operating System :: Microsoft :: Windows
Classifier: Operating System :: POSIX
Classifier: Operating System :: Unix
Classifier: Programming Language :: Python
Classifier: Programming Language :: Python :: 3
Classifier: Programming Language :: Python :: 3 :: Only
Classifier: Programming Language :: Python :: 3.10
Classifier: Programming Language :: Python :: 3.11
Classifier: Programming Language :: Python :: 3.12
Classifier: Programming Language :: C++
Requires-Python: >=3.10
License-File: RealsenseID/LICENSE
License-File: RealsenseID/LicenseNotices/Intel Copyrights.pdf
License-File: RealsenseID/LicenseNotices/TPP for Intel RealSense ID Vision Library Open Source.pdf
License-File: RealsenseID/LicenseNotices/fw/OBL license for Intel RealSense ID Vision Library for Face Authentication (BAO 3.8.21) 1.pdf
License-File: RealsenseID/LicenseNotices/fw/TPP for Intel RealSense ID Vision Library FW.pdf
